{
  "variables": {
    "iso_url": "https://files.gingertechnology.net/packersystems/Win2012R2.iso",
    "iso_checksum_type": "md5",
    "iso_checksum": "0e7c09aab20dec3cd7eab236dab90e78",
    "autounattend": "floppy/server/Autounattend.xml",
    "headless": "false",
    "cpus": "2",
    "memory_size": "4096",
    "disk_size": "40960",
    "exchange_iso": "files/exchange.iso",
    "build_num": "1.0",
    "vmname": "Riordan"
  },
  "builders": [
    {
      "type": "vmware-iso",
      "iso_url": "{{user `iso_url`}}",
      "iso_checksum_type": "{{user `iso_checksum_type`}}",
      "iso_checksum": "{{user `iso_checksum`}}",
      "output_directory": "Builds/{{user `vmname`}}-{{user `build_num`}}",
      "vm_name": "{{user `vmname`}}-{{user `build_num`}}",
      "headless": "{{user `headless`}}",
      "boot_wait": "2m",
      "communicator": "winrm",
      "winrm_username": "GingerTech",
      "winrm_password": "password",
      "winrm_timeout": "6h",
      "shutdown_command": "shutdown /s /t 10 /f /d p:4:1 /c \"Packer Shutdown\"",
      "guest_os_type": "windows8srv-64",
      "tools_upload_flavor": "windows",
      "disk_size": "{{user `disk_size`}}",
      "vnc_port_min": 5900,
      "vnc_port_max": 5980,
      "floppy_files": [
        "{{user `autounattend`}}",
        "floppy/server/00-run-all-scripts.cmd",
        "floppy/server/fixnetwork.ps1",
        "floppy/server/install-winrm.cmd",
        "floppy/server/zz-start-transports.cmd",
        "floppy/server/Update-Needed.ps1",
        "floppy/server/RunPwSh.bat",
        "floppy/update-windows.ps1"
      ],
      "vmx_data": {
        "RemoteDisplay.vnc.enabled": "false",
        "RemoteDisplay.vnc.port": "5900",
        "memsize": "{{user `memory_size`}}",
        "numvcpus": "{{user `cpus`}}",
        "scsi0.virtualDev": "lsisas1068"
      }
    },
    {
      "type": "virtualbox-iso",
      "iso_url": "{{user `iso_url`}}",
      "iso_checksum_type": "{{user `iso_checksum_type`}}",
      "iso_checksum": "{{user `iso_checksum`}}",
      "output_directory": "Builds/{{user `vmname`}}-{{user `build_num`}}",
      "vm_name": "{{user `vmname`}}-{{user `build_num`}}",
      "headless": "{{user `headless`}}",
      "boot_wait": "2m",
      "communicator": "winrm",
      "winrm_username": "GingerTech",
      "winrm_password": "password",
      "winrm_timeout": "6h",
      "shutdown_command": "shutdown /s /t 10 /f /d p:4:1 /c \"Packer Shutdown\"",
      "guest_os_type": "Windows2012_64",
      "disk_size": "{{user `disk_size`}}",
      "floppy_files": [
        "{{user `autounattend`}}",
        "floppy/server/00-run-all-scripts.cmd",
        "floppy/server/fixnetwork.ps1",
        "floppy/server/install-winrm.cmd",
        "floppy/server/zz-start-transports.cmd",
        "floppy/server/Update-Needed.ps1",
        "floppy/server/RunPwSh.bat",
        "floppy/update-windows.ps1"
      ],
      "vboxmanage": [
        [ "modifyvm", "{{.Name}}", "--memory", "{{user `memory_size`}}" ],
        [ "modifyvm", "{{.Name}}", "--cpus", "{{user `cpus`}}" ]
      ]
    }
  ],
  "provisioners": [
    {
      "type": "windows-restart",
      "restart_command": "powershell Restart-Computer -force"
    },
    {
      "type": "file",
      "source": "scripts/winshared/netbullshit.ps1",
      "destination": "C:\\netbullshit.ps1"
    },
    {
      "type": "powershell",
      "elevated_user": "GingerTech",
      "elevated_password": "password",
      "inline": [
        "C:\\netbullshit.ps1 1"
      ]
    },
    {
      "type": "windows-restart",
      "restart_command": "powershell Restart-Computer -force"
    },
    {
      "type": "windows-shell",
      "execute_command": "{{.Vars}} cmd /c C:\\Windows\\Temp\\script.bat",
      "scripts": [
        "scripts/winshared/guest-tools.bat"
      ]
    },
    {
      "type": "windows-restart",
      "restart_command": "powershell Restart-Computer -force"
    },
    {
      "type": "shell-local",
      "only": ["virtualbox-iso"],
      "command": "vboxmanage controlvm {{user `vmname`}}-{{user `build_num`}} poweroff soft && vboxmanage storageattach {{user `vmname`}}-{{user `build_num`}} --storagectl \"IDE Controller\" --port 1 --device 0 --type dvddrive --medium emptydrive && vboxmanage storageattach {{user `vmname`}}-{{user `build_num`}} --storagectl \"IDE Controller\" --port 1 --device 0 --type dvddrive --medium {{user `exchange_iso`}} && vboxmanage startvm {{user `vmname`}}-{{user `build_num`}} && sleep 10"
    },
    {
      "type": "file",
      "source": "files/ninite.exe",
      "destination": "C:\\ninite.exe"
    },
    {
      "type": "file",
      "source": "scripts/winshared/InstallScoop.ps1",
      "destination": "C:\\InstallScoop.ps1"
    },
    {
      "type": "powershell",
      "inline": [
        "powershell -NoLogo -ExecutionPolicy RemoteSigned C:\\InstallScoop.ps1"
      ]
    },
    {
      "type": "windows-restart",
      "restart_command": "powershell Restart-Computer -Force"
    },
    {
      "type": "powershell",
      "inline": [
        "C:\\ninite.exe /locale en-US"
      ]
    },
    {
      "type": "windows-restart",
      "restart_command": "powershell Restart-Computer -Force"
    },
    {
      "type": "powershell",
      "elevated_user": "GingerTech",
      "elevated_password": "password",
      "inline": [
        "C:\\netbullshit.ps1 2"
      ]
    },
    {
      "type": "windows-restart",
      "restart_command": "powershell Restart-Computer -Force"
    },
    {
      "type": "powershell",
      "elevated_user": "GingerTech",
      "elevated_password": "password",
      "inline": [
        "C:\\netbullshit.ps1 3"
      ]
    },
    {
      "type": "windows-restart",
      "restart_command": "powershell Restart-Computer -Force"
    },
    {
      "type": "powershell",
      "elevated_user": "GingerTech",
      "elevated_password": "password",
      "inline": [
        "Install-WindowsFeature ADLDS, RSAT-Clustering-CmdInterface, NET-Framework-45-Features, RPC-over-HTTP-proxy, RSAT-Clustering, RSAT-Clustering-CmdInterface, RSAT-Clustering-Mgmt, RSAT-Clustering-PowerShell, Web-Mgmt-Console, WAS-Process-Model, Web-Asp-Net45, Web-Basic-Auth, Web-Client-Auth, Web-Digest-Auth, Web-Dir-Browsing, Web-Dyn-Compression, Web-Http-Errors, Web-Http-Logging, Web-Http-Redirect, Web-Http-Tracing, Web-ISAPI-Ext, Web-ISAPI-Filter, Web-Lgcy-Mgmt-Console, Web-Metabase, Web-Mgmt-Console, Web-Mgmt-Service, Web-Net-Ext45, Web-Request-Monitor, Web-Server, Web-Stat-Compression, Web-Static-Content, Web-Windows-Auth, Web-WMI, Windows-Identity-Foundation, RSAT-ADDS"
      ]
    },
    {
      "type": "windows-restart",
      "restart_command": "powershell Restart-Computer -Force"
    },
    {
      "type": "powershell",
      "elevated_user": "GingerTech",
      "elevated_password": "password",
      "inline": [
        "choco install -y ucma4"
      ]
    },
    {
      "type": "windows-restart",
      "restart_command": "powershell Restart-Computer -Force"
    },
    {
      "type": "file",
      "source": "files/userlist-win.csv",
      "destination": "C:\\userlist.csv"
    },
    {
      "type": "powershell",
      "elevated_user": "GingerTech",
      "elevated_password": "password",
      "scripts": [
        "scripts/winshared/SetupServ.ps1"
      ]
    },
    {
      "type": "windows-restart",
      "restart_command": "powershell Restart-Computer -Force"
    },
    {
      "type": "powershell",
      "elevated_user": "GingerTech",
      "elevated_password": "password",
      "scripts": [
        "scripts/winshared/exchange.ps1"
      ]
    },
    {
      "type": "windows-restart",
      "restart_command": "powershell Restart-Computer -Force"
    }
  ],
  "post-processors": [
    {
      "type": "manifest",
      "output": "manifest.json",
      "strip_path": true
    }
  ]
}